README.rst
setup.py
bin/hulk
hulk/__init__.py
hulk/application.py
hulk/exceptions.py
hulk/handler.py
hulk/monkey.py
hulk/name.py
hulk/utils.py
hulk/version.py
hulk.egg-info/PKG-INFO
hulk.egg-info/SOURCES.txt
hulk.egg-info/dependency_links.txt
hulk.egg-info/requires.txt
hulk.egg-info/top_level.txt