Metadata-Version: 1.1
Name: hulk
Version: 0.2.2
Summary: Big dumb proxy server for testing service-heavy applications based on requests.
Home-page: https://github.com/Strathcom/hulk
Author: Aaron Fay
Author-email: afay@strathcom.com
License: MIT
Platform: Posix; MacOS X; Windows
Classifier: Development Status :: 4 - Beta
Classifier: Intended Audience :: Developers
Classifier: License :: OSI Approved :: MIT License
Classifier: Operating System :: OS Independent
Classifier: Topic :: Software Development :: Build Tools
Classifier: Topic :: Software Development :: Quality Assurance
Classifier: Topic :: Software Development :: Testing
